Metadata-Version: 2.1
Name: labxpipe
Version: 0.7.1
Summary: Genomics pipelines
Author: Charles E. Vejnar
License: Mozilla Public License 2.0 (MPL 2.0)
Project-URL: homepage, https://git.sr.ht/~vejnar/LabxPipe
Requires-Python: >=3.9
License-File: LICENSE
